{
  "title": "Integrity Construction KC",
  "description": "Family-owned fencing company serving the Greater Kansas City area. Wood privacy, wrought iron, chain link, spaced picket, and specialty fences. We do what we say we will do, when we say we'll do it.",
  "url": "https://www.integrityconstructionkc.com",
  "owner": "Jordan Thompson",
  "email": "jordan@integrityconstructionkc.com",
  "phone": "(970) 978-3236",
  "phonePlain": "9709783236",
  "location": "Kansas City, MO",
  "googleAdsId": "AW-16750455239",
  "tagline": "Beauty. Privacy. Protection. Perfected.",
  "ethos": "We do what we say we will do, by when we say we're going to do it.",
  "values": "Trust | Honor | Integrity"
}
